[
  {
    "id": 1,
    "img": "outmaneuver1",
    "difficulty": 0,
    "answer": "cost",
    "followUp": {
      "question": "What is the actual cost of **_Outmaneuver_**?",
      "choices": {
        "a": "3",
        "b": "2",
        "c": "5",
        "d": "6"
      },
      "answer": "a"
    },
    "actualCard": "SOR/221",
    "explanation": "**_Outmaneuver_** costs 3 resources to play, not 4.",
    "tags": ["outmaneuver", "cost"]
  },
  {
    "id": 2,
    "img": "redthree",
    "difficulty": 1,
    "answer": "ability-text",
    "followUp": {
      "question": "What does **_Red Three, Unstoppable_**, actually do?",
      "choices": {
        "a": "Gives other friendly _Aggression_ units **Raid 2**.",
        "b": "Gives other friendly _Heroism_ units **Raid 1**.",
        "c": "Has **Raid 2** itself.",
        "d": "Gives other friendly _Aggression_ units +1/+0."
      },
      "answer": "b"
    },
    "actualCard": "SOR/144",
    "explanation": "**_Red Three, Unstoppable_** gives friendly _Heroism_ units **Raid 1**, not _Aggression_ units.",
    "tags": ["red three", "ability-text"]
  },
  {
    "id": 3,
    "img": "roguesquadronskirmisher",
    "difficulty": 0,
    "answer": "arena",
    "actualCard": "SOR/101",
    "explanation": "**_Rogue Squadron Skirmisher_** is a Ground unit, not a Space unit.",
    "tags": ["rogue squadron skirmisher", "arena"]
  },
  {
    "id": 4,
    "img": "precisionfire",
    "difficulty": 2,
    "answer": "ability-text",
    "followUp": {
      "question": "What does **_Precision Fire_** actually do?",
      "choices": {
        "a": "The attacking unit has to be a _Trooper_ to gain **Saboteur** as well.",
        "b": "If the attacking unit is a _Trooper_, it gives it **Raid 1** for the attack.",
        "c": "If the attacking unit is a _Trooper_, it gives it +2/+0 for the attack.",
        "d": "If the attacking unit is a _Trooper_, it gives it +1/+0 for the attack."
      },
      "answer": "c"
    },
    "actualCard": "SOR/168",
    "explanation": "If the chosen unit is a _Trooper_, **_Precision Fire_** gives +2/+0, not **Raid 2**.",
    "tags": ["precision fire", "ability-text"]
  },
  {
    "id": 5,
    "img": "blackone1",
    "difficulty": 2,
    "answer": "trigger-condition",
    "followUp": {
      "question": "When does **_Black One, Scourge of Starkiller Base_**, actually trigger?",
      "choices": {
        "a": "**On Attack** only.",
        "b": "**When Played** only.",
        "c": "**On Attack/When Defeated**.",
        "d": "**When Played/When Defeated**."
      },
      "answer": "d"
    },
    "actualCard": "SOR/147",
    "explanation": "**_Black One, Scourge of Starkiller Base's_** ability triggers **When Defeated**, not **On Attack**.",
    "tags": ["black one", "trigger-condition"]
  },
  {
    "id": 6,
    "img": "jedilightsaber",
    "difficulty": 2,
    "answer": "ability-text",
    "followUp": {
      "question": "What is the actual ability text of **_Jedi Lightsaber_**?",
      "choices": {
        "a": "Attach to a _Force_ unit.",
        "b": "If attached unit is a _Jedi_...",
        "c": "Give the defender -2/-2 for this phase.",
        "d": "Give the defender -1/-1 for this attack."
      },
      "answer": "c"
    },
    "actualCard": "SOR/054",
    "explanation": "**_Jedi Lightsaber_** gives the defender -2/-2 for the rest of the entire phase, not just for the attack.",
    "tags": ["jedi lightsaber", "ability-text"]
  },
  {
    "id": 7,
    "img": "vigilance",
    "difficulty": 2,
    "answer": "ability-text",
    "followUp": {
      "question": "Which line of **_Vigilance_** was changed?",
      "choices": {
        "a": "The line about the shield token.",
        "b": "The line about healing a base.",
        "c": "The line about defeating a unit.",
        "d": "The line about discarding cards."
      },
      "answer": "a"
    },
    "actualCard": "SOR/058",
    "explanation": "When choosing to give a shield token with **_Vigilance_**, you can choose to give it to an enemy unit as well, not just friendly.",
    "tags": ["vigilance", "ability-text"]
  },
  {
    "id": 8,
    "img": "darthvader1",
    "difficulty": 1,
    "answer": "something-else",
    "actualCard": "SOR/087",
    "explanation": "The unique symbol is missing from **_Darth Vader's_** name.",
    "tags": ["darth vader", "something-else"]
  },
  {
    "id": 9,
    "img": "atatsuppressor",
    "difficulty": 2,
    "answer": "traits",
    "followUp": {
      "question": "Which of **_AT-AT Suppressor's_** traits is missing/wrong",
      "choices": {
        "a": "_Walker_.",
        "b": "_Imperial_.",
        "c": "_Transport_.",
        "d": "_Republic_."
      },
      "answer": "a"
    },
    "actualCard": "SOR/039",
    "explanation": "**_AT-AT Suppressor_** is missing the _Walker_ trait.",
    "tags": ["at-at suppressor", "traits"]
  },
  {
    "id": 10,
    "img": "theemperorslegion",
    "difficulty": 2,
    "answer": "no-change",
    "actualCard": "SOR/091",
    "explanation": "No changes were made.",
    "tags": ["the emperor's legion", "no-change"]
  },
  {
    "id": 11,
    "img": "superlasertech1",
    "difficulty": 0,
    "answer": "ability-text",
    "followUp": {
      "question": "What does **_Superlaser Technician_** actually do?",
      "choices": {
        "a": "Returns one of your resources to your hand.",
        "b": "Readies one of your exhausted resources.",
        "c": "Puts the top card of your deck into play as a resource.",
        "d": "Can be put into play as a ready resource."
      },
      "answer": "d"
    },
    "actualCard": "SOR/083",
    "explanation": "When **_Superlaser Technician_** is defeated, it becomes a ready resource.",
    "tags": ["superlaser technician", "ability-text"]
  },
  {
    "id": 12,
    "img": "bobafett1",
    "difficulty": 2,
    "answer": "subtitle",
    "followUp": {
      "question": "Do you know what this **_Boba Fett's_** subtitle actually is?",
      "choices": {
        "a": "Any Methods Necessary.",
        "b": "Disintigrator.",
        "c": "Feared Bounty Hunter.",
        "d": "Daimyo."
      },
      "answer": "b"
    },
    "actualCard": "SOR/179",
    "explanation": "This is **_Boba Fett, Disintigrator_**, not **_Boba Fett, Collecting the Bounty_**.",
    "tags": ["boba fett", "subtitle"]
  },
  {
    "id": 13,
    "img": "stormtrooperlieutenant1",
    "difficulty": 0,
    "answer": "name",
    "followUp": {
      "question": "What is the actual name of this card?",
      "choices": {
        "a": "**_First Order Stormtrooper_**.",
        "b": "**_Snowtrooper Vanguard_**.",
        "c": "**_Snowtrooper Lieutenant_**.",
        "d": "**_First Legion Snowtrooper_**."
      },
      "answer": "c"
    },
    "actualCard": "SOR/227",
    "explanation": "This unit's name is actually **_Snowtrooper Liuetenant_**.",
    "tags": ["snowtrooper lieutenant", "name"]
  },
  {
    "id": 14,
    "img": "97thlegion1",
    "difficulty": 2,
    "answer": "aspects",
    "followUp": {
      "question": "What should **_97th Legion's_** aspects actually be?",
      "choices": {
        "a": "Single _Vigilance_.",
        "b": "Single _Aggression_.",
        "c": "Double _Command_.",
        "d": "Single _Command_."
      },
      "answer": "d"
    },
    "actualCard": "SOR/118",
    "explanation": "While **_97th Legion_** does, in fact, have the _Imperial_ trait, it does not have the _Villainy_ aspect.",
    "tags": ["97th legion", "aspects"]
  },
  {
    "id": 15,
    "img": "galacticambition1",
    "difficulty": 1,
    "answer": "no-change",
    "actualCard": "SOR/235",
    "explanation": "No changes were made.",
    "tags": ["galactic ambition", "no-change"]
  },
  {
    "id": 16,
    "img": "bendu1",
    "difficulty": 2,
    "answer": "ability-text",
    "followUp": {
      "question": "What does **_Bendu, The One in the Middle_**, actually do?",
      "choices": {
        "a": "Makes the next non-_Heroism_/non-_Villainy_ card you play cost 2 less.",
        "b": "Makes the next non-_Heroism_/non-_Villainy_ card you play free.",
        "c": "Makes the first non-_Heroism_/non-_Villainy_ card you play each phase cost 1 less.",
        "d": "Makes the first non-_Heroism_/non-_Villainy_ card you play each phase cost 2 less."
      },
      "answer": "a"
    },
    "actualCard": "SOR/056",
    "explanation": "**_Bendu's_** ability discounts the next non-_Heroism_/non-_Villainy_ card you play by 2.",
    "tags": ["bendu", "ability-text"]
  },
  {
    "id": 17,
    "img": "vanguardace1",
    "difficulty": 1,
    "answer": "traits",
    "followUp": {
      "question": "Which of **_Vanguard Ace's_** traits is missing/wrong?",
      "choices": {
        "a": "_Fighter_.",
        "b": "_Rebel_.",
        "c": "_Resistance_.",
        "d": "_Vehicle_."
      },
      "answer": "b"
    },
    "actualCard": "SOR/191",
    "explanation": "**_Vanguard Ace_** is a _New Republic_ unit, not a _Rebel_ unit.",
    "tags": ["vanguard ace", "traits"]
  },
  {
    "id": 18,
    "img": "homeone1",
    "difficulty": 2,
    "answer": "ability-text",
    "followUp": {
      "question": "What does **_Home One, Alliance Flagship_**, actually do?",
      "choices": {
        "a": "It gives other friendly units **Restore 2**.",
        "b": "It should have **Restore 1**.",
        "c": "The unit you play from your discard pile costs 3 less.",
        "d": "The unit you play from your discard pile does not have to be a _Heroism_ unit."
      },
      "answer": "c"
    },
    "actualCard": "SOR/102",
    "explanation": "**_Home One's_** ability does not let you play a unit that costs 3 or less for free, it actually reduces the cost of the unit you play by 3.",
    "tags": ["home one", "ability-text"]
  },
  {
    "id": 19,
    "img": "snowspeeder1",
    "difficulty": 2,
    "answer": "art",
    "followUp": {
      "question": "What's wrong with the art?",
      "choices": {
        "a": "A color was changed.",
        "b": "The art is mirrored.",
        "c": "This art is from a different card.",
        "d": "Something was added/removed."
      },
      "answer": "d"
    },
    "actualCard": "SOR/244",
    "explanation": "A second snowspeeder was removed from the background of the art.",
    "tags": ["snowspeeder", "art"]
  },
  {
    "id": 20,
    "img": "yoda1",
    "difficulty": 0,
    "answer": "ability-text",
    "followUp": {
      "question": "What does **_Yoda, Old Master_**, actually do?",
      "choices": {
        "a": "He gives you the choice to let any player draw a card.",
        "b": "He should have **Restore 1**.",
        "c": "He should have **Restore 3**",
        "d": "He should let you draw 2 cards."
      },
      "answer": "a"
    },
    "actualCard": "SOR/045",
    "explanation": "**_Yoda_** lets you choose any number of players to draw when he is defeated.",
    "tags": ["yoda", "ability-text"]
  },
  {
    "id": 21,
    "img": "openfire1",
    "difficulty": 2,
    "answer": "art",
    "followUp": {
      "question": "What's wrong with the art?",
      "choices": {
        "a": "A color was changed.",
        "b": "The art is mirrored.",
        "c": "This art is from a different card.",
        "d": "Something was added/removed."
      },
      "answer": "b"
    },
    "actualCard": "SOR/172",
    "explanation": "The art has been mirrored.",
    "tags": ["open fire", "art"]
  },
  {
    "id": 22,
    "img": "outlandtievanguard1",
    "difficulty": 1,
    "answer": "ability-text",
    "followUp": {
      "question": "What does **_Outland TIE Vanguard_** actually do?",
      "choices": {
        "a": "It can only give an Experience token to an _Imperial_ unit.",
        "b": "It can only give an Experience token to a unit that costs 2 or less.",
        "c": "It can only give an Experience token to a unit that costs 3 or less.",
        "d": "It gives a shield token."
      },
      "answer": "c"
    },
    "actualCard": "SHD/082",
    "explanation": "**_Outland TIE Vanguard_** can only give Experience tokens to units that cost 3 or less.",
    "tags": ["outland tie vanguard", "ability-text"]
  },
  {
    "id": 23,
    "img": "ketsuonyo1",
    "difficulty": 1,
    "answer": "trigger-condition",
    "followUp": {
      "question": "When does **_Ketsu Onyo, Old Friend_**, actually trigger?",
      "choices": {
        "a": "When attacking and defeating a unit.",
        "b": "When played.",
        "c": "When completing an attack.",
        "d": "When dealing combat damage to a base."
      },
      "answer": "d"
    },
    "actualCard": "SHD/147",
    "explanation": "**_Ketsu's_** ability only triggers when she deals combat damage to a base.",
    "tags": ["ketsu onyo", "trigger-condition"]
  },
  {
    "id": 24,
    "img": "jabbathehutt1",
    "difficulty": 2,
    "answer": "no-change",
    "actualCard": "SOR/181",
    "explanation": "No change has been made.",
    "tags": ["jabba the hutt", "no-change"]
  },
  {
    "id": 25,
    "img": "itbindsallthings1",
    "difficulty": 2,
    "answer": "ability-text",
    "followUp": {
      "question": "What's does **_It Binds All Things_** actually do?",
      "choices": {
        "a": "You only need to control a _Force_ unit.",
        "b": "It can only heal/damage up to 2.",
        "c": "It can heal/damage up to 4.",
        "d": "It can only deal the damage to an enemy unit."
      },
      "answer": "a"
    },
    "actualCard": "SOR/075",
    "explanation": "**_It Binds All Things_** only requires you to _control_ a _Force_ unit, not use the Event on one.",
    "tags": ["it binds all things", "ability-text"]
  },
  {
    "id": 26,
    "img": "chimaera1",
    "difficulty": 1,
    "answer": "hp",
    "followUp": {
      "question": "What is **_Chimaera, Flagship of the Seventh Fleet's_** actual HP?",
      "choices": {
        "a": "9.",
        "b": "7.",
        "c": "6.",
        "d": "10."
      },
      "answer": "b"
    },
    "actualCard": "SOR/185",
    "explanation": "**_Chimaera, Flagship of the Seventh Fleet_**, has 7 HP.",
    "tags": ["chimaera", "hp"]
  },
  {
    "id": 27,
    "img": "maul1",
    "difficulty": 1,
    "answer": "traits",
    "followUp": {
      "question": "Which of **_Maul, Shadow Collective Visionary's_** traits is missing/wrong?",
      "choices": {
        "a": "_Night_.",
        "b": "_Underworld_.",
        "c": "_Sith_.",
        "d": "_Force_."
      },
      "answer": "c"
    },
    "actualCard": "SHD/090",
    "explanation": "**_Maul, Shadow Collective Visionary_**, is not a _Sith_.",
    "tags": ["maul", "traits"]
  },
  {
    "id": 28,
    "img": "aggression1",
    "difficulty": 1,
    "answer": "ability-text",
    "followUp": {
      "question": "Which line of **_Aggression_** was changed?",
      "choices": {
        "a": "The line about readying a unit.",
        "b": "The line about drawing a card.",
        "c": "The line about damaging a unit.",
        "d": "The line about defeating an upgrade."
      },
      "answer": "d"
    },
    "actualCard": "SOR/155",
    "explanation": "**_Aggression's_** second option allows you to defeat \"up to 2\" upgrades.",
    "tags": ["aggression", "ability-text"]
  }

]
